pkg/__init__.py
pkg/_pointer.pyi
pkg/pointer.py
Pointer_pkg_tkchen-0.1.dist-info/METADATA
Pointer_pkg_tkchen-0.1.dist-info/WHEEL
Pointer_pkg_tkchen-0.1.dist-info/top_level.txt
Pointer_pkg_tkchen-0.1.dist-info/RECORD
