Metadata-Version: 2.1
Name: Pointer-pkg-tkchen
Version: 0.1
Summary: A Package that can use the pointers just like in C!
Home-page: https://github.com/chen-tk/Pointer-on-Python
Author: TkChen
Author-email: cccyyyhhh135@outlook.com
Classifier: Programming Language :: Python :: 3
Classifier: License :: OSI Approved :: MIT License
Classifier: Operating System :: OS Independent
Requires-Python: >=3.10
